boxberry/__init__.py
boxberry/client.py
boxberry/exceptions.py
boxberry/utils.py
boxberry-0.1.3.dist-info/METADATA
boxberry-0.1.3.dist-info/WHEEL
boxberry-0.1.3.dist-info/top_level.txt
boxberry-0.1.3.dist-info/RECORD
