Metadata-Version: 2.1
Name: boxberry
Version: 0.1.3
Summary: Клиент для взаимодействия с API Boxberry
Home-page: https://github.com/AlekseevAV/boxberry
Author: Aleksandr Alekseev
Author-email: alekseevavx@gmail.com
License: MIT
Keywords: boxberry
Platform: UNKNOWN
Requires-Dist: requests (==2.18.4)
